matchpy/__init__.py
matchpy/_version.py
matchpy/functions.py
matchpy/utils.py
matchpy/expressions/__init__.py
matchpy/expressions/constraints.py
matchpy/expressions/expressions.py
matchpy/expressions/functions.py
matchpy/expressions/substitution.py
matchpy/matching/__init__.py
matchpy/matching/_common.py
matchpy/matching/bipartite.py
matchpy/matching/code_generation.py
matchpy/matching/hopcroft_karp.py
matchpy/matching/many_to_one.py
matchpy/matching/one_to_one.py
matchpy/matching/syntactic.py
matchpy-0.5.5.dist-info/LICENSE
matchpy-0.5.5.dist-info/METADATA
matchpy-0.5.5.dist-info/WHEEL
matchpy-0.5.5.dist-info/top_level.txt
matchpy-0.5.5.dist-info/zip-safe
matchpy-0.5.5.dist-info/RECORD
