Metadata-Version: 2.1
Name: matchpy
Version: 0.5.5
Summary: A library for pattern matching on symbolic expressions.
Home-page: https://github.com/HPAC/matchpy
Author: Manuel Krebber
Author-email: admin@wheerd.de
License: MIT
Project-URL: Source, https://github.com/HPAC/matchpy
Project-URL: Tracker, https://github.com/HPAC/matchpy/issues
Project-URL: Documentation, https://matchpy.readthedocs.io/
Platform: UNKNOWN
Classifier: Development Status :: 3 - Alpha
Classifier: Intended Audience :: Developers
Classifier: License :: OSI Approved :: MIT License
Classifier: Programming Language :: Python
Classifier: Programming Language :: Python :: 3
Classifier: Programming Language :: Python :: 3.6
Classifier: Programming Language :: Python :: 3.7
Classifier: Programming Language :: Python :: 3.8
Classifier: Programming Language :: Python :: 3.9
Classifier: Programming Language :: Python :: Implementation :: CPython
Requires-Python: >=3.6
Provides-Extra: graphs
Provides-Extra: tests
Provides-Extra: docs
Provides-Extra: develop
License-File: LICENSE
